<net.rptools.maptool.model.Token>
  <id>
    <baGUID>JhoT9eOTSH+X+RdD5OsWkg==</baGUID>
  </id>
  <beingImpersonated>false</beingImpersonated>
  <exposedAreaGUID>
    <baGUID>2vsKwW9xTf+syOmAi6qPaw==</baGUID>
  </exposedAreaGUID>
  <imageAssetMap>
    <entry>
      <null/>
      <net.rptools.lib.MD5Key>
        <id>39765098b9d592c343b790827e9fc954</id>
      </net.rptools.lib.MD5Key>
    </entry>
  </imageAssetMap>
  <x>450</x>
  <y>1500</y>
  <z>46</z>
  <anchorX>0</anchorX>
  <anchorY>0</anchorY>
  <sizeScale>1.0</sizeScale>
  <lastX>0</lastX>
  <lastY>0</lastY>
  <snapToScale>true</snapToScale>
  <width>833</width>
  <height>833</height>
  <isoWidth>833</isoWidth>
  <isoHeight>833</isoHeight>
  <scaleX>1.0</scaleX>
  <scaleY>1.0</scaleY>
  <sizeMap>
    <entry>
      <string>net.rptools.maptool.model.SquareGrid</string>
      <net.rptools.maptool.model.GUID>
        <baGUID>fwABAdBlFSoGAAAAKgABAA==</baGUID>
      </net.rptools.maptool.model.GUID>
    </entry>
  </sizeMap>
  <snapToGrid>true</snapToGrid>
  <isVisible>false</isVisible>
  <visibleOnlyToOwner>false</visibleOnlyToOwner>
  <vblColorSensitivity>-1</vblColorSensitivity>
  <alwaysVisibleTolerance>2</alwaysVisibleTolerance>
  <isAlwaysVisible>false</isAlwaysVisible>
  <name>Kron Hills Gnomes</name>
  <ownerList/>
  <ownerType>0</ownerType>
  <tokenShape>TOP_DOWN</tokenShape>
  <tokenType>NPC</tokenType>
  <layer>TOKEN</layer>
  <propertyType>Basic</propertyType>
  <tokenOpacity>1.0</tokenOpacity>
  <speechName></speechName>
  <terrainModifier>0.0</terrainModifier>
  <terrainModifierOperation>NONE</terrainModifierOperation>
  <terrainModifiersIgnored>
    <net.rptools.maptool.model.Token_-TerrainModifierOperation>NONE</net.rptools.maptool.model.Token_-TerrainModifierOperation>
  </terrainModifiersIgnored>
  <isFlippedX>false</isFlippedX>
  <isFlippedY>false</isFlippedY>
  <isFlippedIso>false</isFlippedIso>
  <lightSourceList/>
  <sightType>Normal</sightType>
  <hasSight>false</hasSight>
  <hasImageTable>false</hasImageTable>
  <notes></notes>
  <notesType>text/plain</notesType>
  <gmNotes></gmNotes>
  <gmNotesType>text/plain</gmNotesType>
  <gmName></gmName>
  <state/>
  <propertyMapCI>
    <store/>
  </propertyMapCI>
  <macroPropertiesMap/>
  <speechMap/>
  <allowURIAccess>false</allowURIAccess>
</net.rptools.maptool.model.Token>
